<?xml version="1.0" encoding="UTF-8"?>
<CONF xmlns="www.rbin.com/mds-1" xmlns:xsi="http://www.w3.org/2001/XMLSchema-instance" xsi:schemaLocation="www.rbin.com/mds-1
.\schemas\baseio.xsd">
<!-- This is the input to the baseio dll -->
	<HEXMOD>
		<BASEIO>
			<INPUT>
<FILEIN TYPE="IHEX" NAME="_buildgen\Output\NewEagle_ME1735_810D0_8A13_linker.hex" IGNORELINECKS="true" />
<FILEIN TYPE="IHEX" NAME="hex_files\cb_int.hex" IGNORELINECKS="true" />
<FILEIN TYPE="IHEX" NAME="hex_files\hsb_auto_conf.hex" IGNORELINECKS="true" />
<FILEIN TYPE="IHEX" NAME="hex_files\sb_auto_conf.hex" IGNORELINECKS="true" />
<FILEIN TYPE="IHEX" NAME="hex_files\tprot_auto_conf.hex" IGNORELINECKS="true" />
<FILEIN TYPE="IHEX" NAME="hex_files\tprot_auto_src_conf.hex" IGNORELINECKS="true" >
<MEM ACTION="COPY" FROM="0x80000000" LEN="0xFC78" TO="0x80000000" OVERWRITE="true" FILLGAPS="0x00"/>
<MEM ACTION="COPY" FROM="0x8000FC78" LEN="0x8C" TO="0x8000FC78" OVERWRITE="true" FILLGAPS="0x00"/>
<MEM ACTION="COPY" FROM="0x8000FD04" LEN="0x2FC" TO="0x8000FD04" OVERWRITE="true" FILLGAPS="0x00"/>
<MEM ACTION="COPY" FROM="0x80010000" LEN="0x4000" TO="0x80010000" OVERWRITE="true" FILLGAPS="0x00"/>
<MEM ACTION="COPY" FROM="0x80014000" LEN="0x3E74" TO="0x80014000" OVERWRITE="true" FILLGAPS="0x00"/>
<MEM ACTION="COPY" FROM="0x80017E74" LEN="0x18C" TO="0x80017E74" OVERWRITE="true" FILLGAPS="0x00"/>
<MEM ACTION="COPY" FROM="0x80018000" LEN="0x7E74" TO="0x80018000" OVERWRITE="true" FILLGAPS="0x00"/>
<MEM ACTION="COPY" FROM="0x8001FE74" LEN="0x18C" TO="0x8001FE74" OVERWRITE="true" FILLGAPS="0x00"/>
<MEM ACTION="COPY" FROM="0x80020000" LEN="0x1DFF74" TO="0x80020000" OVERWRITE="true" FILLGAPS="0x00"/>
<MEM ACTION="COPY" FROM="0x801FFF74" LEN="0x8C" TO="0x801FFF74" OVERWRITE="true" FILLGAPS="0x00"/>
<MEM ACTION="COPY" FROM="0x80800000" LEN="0x17FF74" TO="0x80800000" OVERWRITE="true" FILLGAPS="0x00"/>
<MEM ACTION="COPY" FROM="0x8097FF74" LEN="0x8C" TO="0x8097FF74" OVERWRITE="true" FILLGAPS="0x00"/>
<MEM ACTION="COPY" FROM="0x80980000" LEN="0x7BF74" TO="0x80980000" OVERWRITE="true" FILLGAPS="0x00"/>
<MEM ACTION="COPY" FROM="0x809FBF74" LEN="0x8C" TO="0x809FBF74" OVERWRITE="true" FILLGAPS="0x00"/>
<MEM ACTION="COPY" FROM="0x809FC000" LEN="0x4000" TO="0x809FC000" OVERWRITE="true" FILLGAPS="0x00"/>
				</FILEIN>
			</INPUT>
		</BASEIO>
	</HEXMOD>
</CONF>
